sentidict/#dictionaries.py#
sentidict/__init__.py
sentidict/dictionaries.py
sentidict/functions.py
sentidict/pdfify.js
sentidict/shift-crowbar.js
sentidict/utils.py
sentidict/wordshifts.py
sentidict/data/AFINN/AFINN-111.txt.gz
sentidict/data/ANEW/all-2.csv.gz
sentidict/data/EmoSenticNet/emosenticnet.csv.gz
sentidict/data/Emoticons/negative.txt.gz
sentidict/data/Emoticons/neutral.txt.gz
sentidict/data/Emoticons/positive.txt.gz
sentidict/data/GI/inqtabs.txt.gz
sentidict/data/LabMT/labMT2arabic.txt.gz
sentidict/data/LabMT/labMT2chinese.txt.gz
sentidict/data/LabMT/labMT2english.txt.gz
sentidict/data/LabMT/labMT2french.txt.gz
sentidict/data/LabMT/labMT2german.txt.gz
sentidict/data/LabMT/labMT2hindi.txt.gz
sentidict/data/LabMT/labMT2indonesian.txt.gz
sentidict/data/LabMT/labMT2korean.txt.gz
sentidict/data/LabMT/labMT2pashto.txt.gz
sentidict/data/LabMT/labMT2portuguese.txt.gz
sentidict/data/LabMT/labMT2russian.txt.gz
sentidict/data/LabMT/labMT2spanish.txt.gz
sentidict/data/LabMT/labMT2urdu.txt.gz
sentidict/data/MPQA/subjclueslen1-HLTEMNLP05.tff.gz
sentidict/data/NRC/Maxdiff-Twitter-Lexicon_-1to1.txt.gz
sentidict/data/NRC/NRC-emotion-lexicon-wordlevel-alphabetized-v0.92.txt.gz
sentidict/data/NRC/NRC-Hashtag-Sentiment-Lexicon-v0.1/unigrams-pmilexicon.txt.gz
sentidict/data/NRC/Sentiment140-Lexicon-v0.1/bigrams-pmilexicon.txt.gz
sentidict/data/NRC/Sentiment140-Lexicon-v0.1/pairs-pmilexicon.txt.gz
sentidict/data/NRC/Sentiment140-Lexicon-v0.1/unigrams-pmilexicon.txt.gz
sentidict/data/OL/negative-words.txt.gz
sentidict/data/OL/positive-words.txt.gz
sentidict/data/PANAS-X/affect.txt.gz
sentidict/data/Pattern/en-sentiment.xml.gz
sentidict/data/SOCAL/all_dictionaries-utf8.txt.gz
sentidict/data/SentiStrength/EmoticonLookupTable-utf8.txt.gz
sentidict/data/SentiStrength/EmotionLookupTable.txt.gz
sentidict/data/SentiWordNet/SentiWordNet_3.0.0_20130122.txt.gz
sentidict/data/SenticNet/senticnet3.json.gz
sentidict/data/USent/negative.txt.gz
sentidict/data/USent/positive.txt.gz
sentidict-0.1.13.dist-info/METADATA
sentidict-0.1.13.dist-info/WHEEL
sentidict-0.1.13.dist-info/licenses/LICENSE.md
sentidict-0.1.13.dist-info/RECORD
