Metadata-Version: 2.4
Name: sentidict
Version: 0.1.13
Summary: Utilities for dictionary-based sentiment analysis. Includes 28 sentiment dictionaries with loaders, scoring, and interactive visualization.
Project-URL: Documentation, https://sentidict.readthedocs.io/
Project-URL: Repository, https://github.com/andyreagan/sentidict
Project-URL: Issues, https://github.com/andyreagan/sentidict/issues
Author-email: Andy Reagan <andy@andyreagan.com>
License: ## creative commons
License-File: LICENSE.md
Keywords: emotion,nlp,sentiment,text-analysis
Classifier: Development Status :: 4 - Beta
Classifier: Intended Audience :: Science/Research
Classifier: License :: OSI Approved :: MIT License
Classifier: Operating System :: OS Independent
Classifier: Programming Language :: Python :: 3
Classifier: Programming Language :: Python :: 3.9
Classifier: Programming Language :: Python :: 3.10
Classifier: Programming Language :: Python :: 3.11
Classifier: Programming Language :: Python :: 3.12
Requires-Python: >=3.9
Requires-Dist: jinja2
Requires-Dist: marisa-trie
Requires-Dist: numpy
Provides-Extra: dev
Requires-Dist: black>=22.1.0; extra == 'dev'
Requires-Dist: flake8>=4.0.1; extra == 'dev'
Requires-Dist: ipython; extra == 'dev'
Requires-Dist: isort>=5.10.1; extra == 'dev'
Requires-Dist: twine; extra == 'dev'
Provides-Extra: docs
Requires-Dist: ipython>=7.0.0; extra == 'docs'
Requires-Dist: myst-parser>=0.18.0; extra == 'docs'
Requires-Dist: sphinx-rtd-theme>=1.0.0; extra == 'docs'
Requires-Dist: sphinx>=4.0.0; extra == 'docs'
Provides-Extra: test
Requires-Dist: jupyter; extra == 'test'
Requires-Dist: pytest-cov>=4.0.0; extra == 'test'
Requires-Dist: pytest>=7.0.0; extra == 'test'
Requires-Dist: scipy; extra == 'test'
